superannotate_schemas/__init__.py
superannotate_schemas/__main__.py
superannotate_schemas/_format.py
superannotate_schemas/_legacy_validators.py
superannotate_schemas/_reflect.py
superannotate_schemas/_types.py
superannotate_schemas/_utils.py
superannotate_schemas/_validators.py
superannotate_schemas/compat.py
superannotate_schemas/exceptions.py
superannotate_schemas/validators.py
superannotate_schemas/schemas/draft3.json
superannotate_schemas/schemas/draft4.json
superannotate_schemas/schemas/draft6.json
superannotate_schemas/schemas/draft7.json
superannotate_schemas/tests/__init__.py
superannotate_schemas/tests/_helpers.py
superannotate_schemas/tests/test_exceptions.py
superannotate_schemas/tests/test_format.py
superannotate_schemas/tests/test_jsonschema_test_suite.py
superannotate_schemas/tests/test_types.py
superannotate_schemas-1.0.49.dist-info/METADATA
superannotate_schemas-1.0.49.dist-info/WHEEL
superannotate_schemas-1.0.49.dist-info/entry_points.txt
superannotate_schemas-1.0.49.dist-info/top_level.txt
superannotate_schemas-1.0.49.dist-info/RECORD
