Metadata-Version: 2.1
Name: superannotate-schemas
Version: 1.0.49
Summary: SuperAnnotate JSON Schemas
Home-page: https://www.superannotate.com/
Author: Vaghinak Basentsyan
Author-email: vaghinak@superannotate.con
License: MIT
Requires-Dist: pyrsistent ~=0.20.0
